topsis/__init__.py
topsis/topsis.py
topsis_arshia_102303144-1.0.0.dist-info/licenses/LICENSE
topsis_arshia_102303144-1.0.0.dist-info/METADATA
topsis_arshia_102303144-1.0.0.dist-info/WHEEL
topsis_arshia_102303144-1.0.0.dist-info/entry_points.txt
topsis_arshia_102303144-1.0.0.dist-info/top_level.txt
topsis_arshia_102303144-1.0.0.dist-info/RECORD
