Metadata-Version: 2.4
Name: Topsis-Arshia-102303144
Version: 1.0.0
Summary: Python package for solving MCDM problems using TOPSIS
Author: Arshia Anand
License: MIT
Requires-Python: >=3.7
License-File: LICENSE
Requires-Dist: pandas
Requires-Dist: numpy
Requires-Dist: openpyxl
Dynamic: author
Dynamic: description
Dynamic: description-content-type
Dynamic: license
Dynamic: license-file
Dynamic: requires-dist
Dynamic: requires-python
Dynamic: summary
